py_trees_js/__init__.py
py_trees_js/gen.bash
py_trees_js/resources.py
py_trees_js/resources.qrc
py_trees_js/viewer/__init__.py
py_trees_js/viewer/console.py
py_trees_js/viewer/gen.bash
py_trees_js/viewer/html/index.html
py_trees_js/viewer/images/tuxrobot.png
py_trees_js/viewer/images.qrc
py_trees_js/viewer/images_rc.py
py_trees_js/viewer/main_window.py
py_trees_js/viewer/main_window.ui
py_trees_js/viewer/main_window_ui.py
py_trees_js/viewer/trees.py
py_trees_js/viewer/viewer.py
py_trees_js/viewer/web_app.qrc
py_trees_js/viewer/web_app_rc.py
py_trees_js/viewer/web_view.py
py_trees_js/viewer/web_view.ui
py_trees_js/viewer/web_view_ui.py
py_trees_js-0.6.6.dist-info/LICENSE
py_trees_js-0.6.6.dist-info/METADATA
py_trees_js-0.6.6.dist-info/WHEEL
py_trees_js-0.6.6.dist-info/entry_points.txt
py_trees_js-0.6.6.dist-info/RECORD
