Metadata-Version: 2.3
Name: py_trees_js
Version: 0.6.6
Summary: javascript libraries for visualising behaviour trees
License: BSD
Keywords: py_trees,py-trees,behaviour-trees
Author: Daniel Stonier
Maintainer: Daniel Stonier
Maintainer-email: d.stonier@gmail.com
Requires-Python: >=3.8,<4.0
Classifier: Intended Audience :: Developers
Classifier: License :: OSI Approved :: BSD License
Classifier: License :: Other/Proprietary License
Classifier: Programming Language :: Python
Classifier: Programming Language :: Python :: 3
Classifier: Programming Language :: Python :: 3.8
Classifier: Programming Language :: Python :: 3.9
Classifier: Programming Language :: Python :: 3.10
Classifier: Programming Language :: Python :: 3.11
Classifier: Programming Language :: Python :: 3.12
Classifier: Programming Language :: Python :: 3.13
Classifier: Topic :: Scientific/Engineering :: Artificial Intelligence
Classifier: Topic :: Software Development :: Libraries
Requires-Dist: pyqt5 (>=5.14,<5.15)
Requires-Dist: pyqtwebengine (>=5.14,<5.15)
Project-URL: Documentation, https://github.com/splintered-reality/py_trees_js
Project-URL: Homepage, https://github.com/splintered-reality/py_trees_js
Project-URL: Repository, https://github.com/splintered-reality/py_trees_js
